django_hugeicons_stroke/__init__.py
django_hugeicons_stroke/admin.py
django_hugeicons_stroke/apps.py
django_hugeicons_stroke/templatetags/__init__.py
django_hugeicons_stroke/templatetags/hugeicons_stroke.py
django_hugeicons_stroke/templatetags/stroke_icons.py
django_hugeicons_stroke-1.1.2.dist-info/METADATA
django_hugeicons_stroke-1.1.2.dist-info/WHEEL
django_hugeicons_stroke-1.1.2.dist-info/top_level.txt
django_hugeicons_stroke-1.1.2.dist-info/RECORD
